{
    "547782677793734656": {
        "COLOR": "0x0000FF",
        "ErCOLOR": "0x8B0000",
        "JoinRoles": [],
        "ROLES": {},
        "actmoduls": "",
        "nCaps": -1,
        "nWarns": 10,
        "idAdminchennel": "0",
        "idMainch": "0",
        "selfRoom": "0",
        "BADWORDS": [],
        "LINKS": [],
        "PREFIX": "~",
        "JNMSG": "",
        "SelfTitle": "*\u0412\u044b\u0431\u0435\u0440\u0438\u0442\u0435 \u0432\u0430\u0448\u0438 \u0440\u043e\u043b\u0438:* ",
        "Selfrooms": {},
        "Mafrooms": {},
        "IgnoreChannels": [],
        "IgnoreRoles": [],
        "card": "wave.png",
        "text_color": "#d0ed2b",
        "bar_color": "#ec5252",
        "blend": 1,
        "USERS": {
            "466609421863354388": {
                "WARNS": 0,
                "CAPS": 0,
                "SCR": 0,
                "LvL": 1
            },
            "776179079221084180": {
                "WARNS": 0,
                "CAPS": 0,
                "SCR": 0,
                "LvL": 1
            },
            "359774801784602628": {
                "WARNS": 0,
                "CAPS": 0,
                "SCR": 0,
                "LvL": 1
            },
            "330050349408845825": {
                "WARNS": 0,
                "CAPS": 0,
                "SCR": 0,
                "LvL": 1
            },
            "758734389072625685": {
                "WARNS": 0,
                "CAPS": 0,
                "SCR": 0,
                "LvL": 1
            },
            "243063451751153664": {
                "WARNS": 0,
                "CAPS": 0,
                "SCR": 0,
                "LvL": 1
            },
            "789220420237656124": {
                "WARNS": 0,
                "CAPS": 0,
                "SCR": 0,
                "LvL": 1
            },
            "539848793693224970": {
                "WARNS": 0,
                "CAPS": 0,
                "SCR": 0,
                "LvL": 1
            },
            "858638662160613376": {
                "WARNS": 0,
                "CAPS": 0,
                "SCR": 0,
                "LvL": 1
            },
            "742045972280115231": {
                "WARNS": 0,
                "CAPS": 0,
                "SCR": 0,
                "LvL": 1
            },
            "576788775846412304": {
                "WARNS": 0,
                "CAPS": 0,
                "SCR": 0,
                "LvL": 1
            },
            "184405311681986560": {
                "WARNS": 0,
                "CAPS": 0,
                "SCR": 0,
                "LvL": 1
            },
            "243062080981172224": {
                "WARNS": 0,
                "CAPS": 0,
                "SCR": 0,
                "LvL": 1
            },
            "435554379207278613": {
                "WARNS": 0,
                "CAPS": 0,
                "SCR": 0,
                "LvL": 1
            },
            "404597024923713536": {
                "WARNS": 0,
                "CAPS": 0,
                "SCR": 0,
                "LvL": 1
            },
            "421668402281840650": {
                "WARNS": 0,
                "CAPS": 0,
                "SCR": 0,
                "LvL": 1
            },
            "441864509238542346": {
                "WARNS": 0,
                "CAPS": 0,
                "SCR": 0,
                "LvL": 1
            },
            "558289854514069504": {
                "WARNS": 0,
                "CAPS": 0,
                "SCR": 0,
                "LvL": 1
            },
            "701912803950198925": {
                "WARNS": 0,
                "CAPS": 0,
                "SCR": 0,
                "LvL": 1
            },
            "298777154479718403": {
                "WARNS": 0,
                "CAPS": 0,
                "SCR": 0,
                "LvL": 1
            },
            "694136874230349845": {
                "WARNS": 0,
                "CAPS": 0,
                "SCR": 0,
                "LvL": 1
            },
            "558701945523798040": {
                "WARNS": 0,
                "CAPS": 0,
                "SCR": 0,
                "LvL": 1
            },
            "482875255761928202": {
                "WARNS": 0,
                "CAPS": 0,
                "SCR": 0,
                "LvL": 1
            },
            "806765553221107712": {
                "WARNS": 0,
                "CAPS": 0,
                "SCR": 0,
                "LvL": 1
            },
            "718145295916990544": {
                "WARNS": 0,
                "CAPS": 0,
                "SCR": 0,
                "LvL": 1
            },
            "406124614729859073": {
                "WARNS": 0,
                "CAPS": 0,
                "SCR": 0,
                "LvL": 1
            },
            "396331698352160778": {
                "WARNS": 0,
                "CAPS": 0,
                "SCR": 0,
                "LvL": 1
            },
            "992771455500681307": {
                "WARNS": 0,
                "CAPS": 0,
                "SCR": 0,
                "LvL": 1
            },
            "281070552465145857": {
                "WARNS": 0,
                "CAPS": 0,
                "SCR": 0,
                "LvL": 1
            },
            "136845059717988354": {
                "WARNS": 0,
                "CAPS": 0,
                "SCR": 0,
                "LvL": 1
            },
            "653654221438320642": {
                "WARNS": 0,
                "CAPS": 0,
                "SCR": 0,
                "LvL": 1
            },
            "224930494314315776": {
                "WARNS": 0,
                "CAPS": 0,
                "SCR": 0,
                "LvL": 1
            },
            "583722104059592757": {
                "WARNS": 0,
                "CAPS": 0,
                "SCR": 0,
                "LvL": 1
            },
            "666768779174346782": {
                "WARNS": 0,
                "CAPS": 0,
                "SCR": 0,
                "LvL": 1
            },
            "352413086096818176": {
                "WARNS": 0,
                "CAPS": 0,
                "SCR": 0,
                "LvL": 1
            },
            "600233071052324883": {
                "WARNS": 0,
                "CAPS": 0,
                "SCR": 0,
                "LvL": 1
            },
            "815969322760667227": {
                "WARNS": 0,
                "CAPS": 0,
                "SCR": 0,
                "LvL": 1
            },
            "539839705412272138": {
                "WARNS": 0,
                "CAPS": 0,
                "SCR": 0,
                "LvL": 1
            },
            "507525967171026954": {
                "WARNS": 0,
                "CAPS": 0,
                "SCR": 0,
                "LvL": 1
            },
            "491983334419857426": {
                "WARNS": 0,
                "CAPS": 0,
                "SCR": 0,
                "LvL": 1
            },
            "786296552620556329": {
                "WARNS": 0,
                "CAPS": 0,
                "SCR": 0,
                "LvL": 1
            },
            "968837189972676669": {
                "WARNS": 0,
                "CAPS": 0,
                "SCR": 0,
                "LvL": 1
            },
            "407114122946150400": {
                "WARNS": 0,
                "CAPS": 0,
                "SCR": 0,
                "LvL": 1
            },
            "692071425728708618": {
                "WARNS": 0,
                "CAPS": 0,
                "SCR": 0,
                "LvL": 1
            },
            "544279889470291989": {
                "WARNS": 0,
                "CAPS": 0,
                "SCR": 0,
                "LvL": 1
            },
            "969620718574784522": {
                "WARNS": 0,
                "CAPS": 0,
                "SCR": 0,
                "LvL": 1
            },
            "347027993530728448": {
                "WARNS": 0,
                "CAPS": 0,
                "SCR": 0,
                "LvL": 1
            },
            "266874383732047872": {
                "WARNS": 0,
                "CAPS": 0,
                "SCR": 0,
                "LvL": 1
            },
            "758724686497579100": {
                "WARNS": 0,
                "CAPS": 0,
                "SCR": 0,
                "LvL": 1
            },
            "204255221017214977": {
                "WARNS": 0,
                "CAPS": 0,
                "SCR": 0,
                "LvL": 1
            },
            "445598738266718218": {
                "WARNS": 0,
                "CAPS": 0,
                "SCR": 0,
                "LvL": 1
            },
            "320904078555217920": {
                "WARNS": 0,
                "CAPS": 0,
                "SCR": 0,
                "LvL": 1
            },
            "935190075430543461": {
                "WARNS": 0,
                "CAPS": 0,
                "SCR": 0,
                "LvL": 1
            },
            "666401889419657265": {
                "WARNS": 0,
                "CAPS": 0,
                "SCR": 0,
                "LvL": 1
            },
            "640846464427229184": {
                "WARNS": 0,
                "CAPS": 0,
                "SCR": 0,
                "LvL": 1
            },
            "639517763362226176": {
                "WARNS": 0,
                "CAPS": 0,
                "SCR": 0,
                "LvL": 1
            },
            "547785297690099742": {
                "WARNS": 0,
                "CAPS": 0,
                "SCR": 0,
                "LvL": 1
            },
            "678681421874855956": {
                "WARNS": 0,
                "CAPS": 0,
                "SCR": 0,
                "LvL": 1
            },
            "775110596584538193": {
                "WARNS": 0,
                "CAPS": 0,
                "SCR": 0,
                "LvL": 1
            },
            "498214011385675777": {
                "WARNS": 0,
                "CAPS": 0,
                "SCR": 0,
                "LvL": 1
            },
            "263363253906702337": {
                "WARNS": 0,
                "CAPS": 0,
                "SCR": 0,
                "LvL": 1
            },
            "249522645782102017": {
                "WARNS": 0,
                "CAPS": 0,
                "SCR": 0,
                "LvL": 1
            },
            "547077175308713994": {
                "WARNS": 0,
                "CAPS": 0,
                "SCR": 0,
                "LvL": 1
            },
            "502484326080839690": {
                "WARNS": 0,
                "CAPS": 0,
                "SCR": 0,
                "LvL": 1
            },
            "594614625128022021": {
                "WARNS": 0,
                "CAPS": 0,
                "SCR": 0,
                "LvL": 1
            },
            "454968668808544267": {
                "WARNS": 0,
                "CAPS": 0,
                "SCR": 0,
                "LvL": 1
            },
            "258197323312529409": {
                "WARNS": 0,
                "CAPS": 0,
                "SCR": 0,
                "LvL": 1
            },
            "562710671628697621": {
                "WARNS": 0,
                "CAPS": 0,
                "SCR": 0,
                "LvL": 1
            },
            "509388836670013466": {
                "WARNS": 0,
                "CAPS": 0,
                "SCR": 0,
                "LvL": 1
            },
            "514126627639394306": {
                "WARNS": 0,
                "CAPS": 0,
                "SCR": 0,
                "LvL": 1
            },
            "313723235843833856": {
                "WARNS": 0,
                "CAPS": 0,
                "SCR": 0,
                "LvL": 1
            },
            "469068799681888286": {
                "WARNS": 0,
                "CAPS": 0,
                "SCR": 0,
                "LvL": 1
            },
            "984816758441517157": {
                "WARNS": 0,
                "CAPS": 0,
                "SCR": 0,
                "LvL": 1
            },
            "747389258393714729": {
                "WARNS": 0,
                "CAPS": 0,
                "SCR": 0,
                "LvL": 1
            },
            "565523599700787210": {
                "WARNS": 0,
                "CAPS": 0,
                "SCR": 0,
                "LvL": 1
            },
            "549163915506876426": {
                "WARNS": 0,
                "CAPS": 0,
                "SCR": 0,
                "LvL": 1
            },
            "398167900994928650": {
                "WARNS": 0,
                "CAPS": 0,
                "SCR": 0,
                "LvL": 1
            },
            "745352462604697668": {
                "WARNS": 0,
                "CAPS": 0,
                "SCR": 0,
                "LvL": 1
            },
            "796004215197007892": {
                "WARNS": 0,
                "CAPS": 0,
                "SCR": 0,
                "LvL": 1
            }
        }
    },
    "705375538570723328": {
        "COLOR": "0x0000FF",
        "ErCOLOR": "0x8B0000",
        "JoinRoles": [],
        "ROLES": {},
        "actmoduls": "",
        "nCaps": -1,
        "nWarns": 10,
        "idAdminchennel": "0",
        "idMainch": "0",
        "selfRoom": "0",
        "BADWORDS": [],
        "LINKS": [],
        "PREFIX": "~",
        "JNMSG": "",
        "SelfTitle": "*\u0412\u044b\u0431\u0435\u0440\u0438\u0442\u0435 \u0432\u0430\u0448\u0438 \u0440\u043e\u043b\u0438:* ",
        "Selfrooms": {},
        "Mafrooms": {},
        "IgnoreChannels": [],
        "IgnoreRoles": [],
        "card": "wave.png",
        "text_color": "#d0ed2b",
        "bar_color": "#ec5252",
        "blend": 1,
        "USERS": {
            "758734389072625685": {
                "WARNS": 0,
                "CAPS": 0,
                "SCR": 0,
                "LvL": 1
            },
            "450998896471048193": {
                "WARNS": 0,
                "CAPS": 0,
                "SCR": 0,
                "LvL": 1
            },
            "539848793693224970": {
                "WARNS": 0,
                "CAPS": 0,
                "SCR": 0,
                "LvL": 1
            },
            "773875536627630090": {
                "WARNS": 0,
                "CAPS": 0,
                "SCR": 0,
                "LvL": 1
            },
            "704059929413287978": {
                "WARNS": 0,
                "CAPS": 0,
                "SCR": 0,
                "LvL": 1
            },
            "742045972280115231": {
                "WARNS": 0,
                "CAPS": 0,
                "SCR": 0,
                "LvL": 1
            },
            "728490855173980191": {
                "WARNS": 0,
                "CAPS": 0,
                "SCR": 0,
                "LvL": 1
            },
            "516006809807486996": {
                "WARNS": 0,
                "CAPS": 0,
                "SCR": 0,
                "LvL": 1
            },
            "282981504261423104": {
                "WARNS": 0,
                "CAPS": 0,
                "SCR": 0,
                "LvL": 1
            },
            "356017045693005827": {
                "WARNS": 0,
                "CAPS": 0,
                "SCR": 0,
                "LvL": 1
            },
            "418472829114122241": {
                "WARNS": 0,
                "CAPS": 0,
                "SCR": 0,
                "LvL": 1
            },
            "586288718684487701": {
                "WARNS": 0,
                "CAPS": 0,
                "SCR": 0,
                "LvL": 1
            },
            "707451192082563093": {
                "WARNS": 0,
                "CAPS": 0,
                "SCR": 0,
                "LvL": 1
            },
            "770710296410980392": {
                "WARNS": 0,
                "CAPS": 0,
                "SCR": 0,
                "LvL": 1
            },
            "406124614729859073": {
                "WARNS": 0,
                "CAPS": 0,
                "SCR": 0,
                "LvL": 1
            },
            "682284139080450166": {
                "WARNS": 0,
                "CAPS": 0,
                "SCR": 0,
                "LvL": 1
            },
            "666768779174346782": {
                "WARNS": 0,
                "CAPS": 0,
                "SCR": 0,
                "LvL": 1
            },
            "352413086096818176": {
                "WARNS": 0,
                "CAPS": 0,
                "SCR": 0,
                "LvL": 1
            },
            "548396516579213312": {
                "WARNS": 0,
                "CAPS": 0,
                "SCR": 0,
                "LvL": 1
            },
            "430702358402564097": {
                "WARNS": 0,
                "CAPS": 0,
                "SCR": 0,
                "LvL": 1
            },
            "466609421863354388": {
                "WARNS": 0,
                "CAPS": 0,
                "SCR": 0,
                "LvL": 1
            },
            "826878276420894740": {
                "WARNS": 0,
                "CAPS": 0,
                "SCR": 0,
                "LvL": 1
            },
            "815969322760667227": {
                "WARNS": 0,
                "CAPS": 0,
                "SCR": 0,
                "LvL": 1
            },
            "852579428990058516": {
                "WARNS": 0,
                "CAPS": 0,
                "SCR": 0,
                "LvL": 1
            },
            "565136716206178305": {
                "WARNS": 0,
                "CAPS": 0,
                "SCR": 0,
                "LvL": 1
            },
            "495221623654318080": {
                "WARNS": 0,
                "CAPS": 0,
                "SCR": 0,
                "LvL": 1
            },
            "418423687788756996": {
                "WARNS": 0,
                "CAPS": 0,
                "SCR": 0,
                "LvL": 1
            },
            "775110596584538193": {
                "WARNS": 0,
                "CAPS": 0,
                "SCR": 0,
                "LvL": 1
            },
            "724964109694795796": {
                "WARNS": 0,
                "CAPS": 0,
                "SCR": 0,
                "LvL": 1
            },
            "678649093165416464": {
                "WARNS": 0,
                "CAPS": 0,
                "SCR": 0,
                "LvL": 1
            },
            "639506131579961374": {
                "WARNS": 0,
                "CAPS": 0,
                "SCR": 0,
                "LvL": 1
            },
            "873227093834620958": {
                "WARNS": 0,
                "CAPS": 0,
                "SCR": 0,
                "LvL": 1
            },
            "550303318887628822": {
                "WARNS": 0,
                "CAPS": 0,
                "SCR": 0,
                "LvL": 1
            },
            "984816758441517157": {
                "WARNS": 0,
                "CAPS": 0,
                "SCR": 0,
                "LvL": 1
            },
            "675596035694788608": {
                "WARNS": 0,
                "CAPS": 0,
                "SCR": 0,
                "LvL": 1
            },
            "514329860852809740": {
                "WARNS": 0,
                "CAPS": 0,
                "SCR": 0,
                "LvL": 1
            },
            "644134412354715668": {
                "WARNS": 0,
                "CAPS": 0,
                "SCR": 0,
                "LvL": 1
            },
            "796004215197007892": {
                "WARNS": 0,
                "CAPS": 0,
                "SCR": 0,
                "LvL": 1
            }
        }
    },
    "812800677637652525": {
        "COLOR": "0x0000FF",
        "ErCOLOR": "0x8B0000",
        "JoinRoles": [],
        "ROLES": {},
        "actmoduls": "",
        "nCaps": -1,
        "nWarns": 10,
        "idAdminchennel": "0",
        "idMainch": "0",
        "selfRoom": "0",
        "BADWORDS": [],
        "LINKS": [],
        "PREFIX": "~",
        "JNMSG": "",
        "SelfTitle": "*\u0412\u044b\u0431\u0435\u0440\u0438\u0442\u0435 \u0432\u0430\u0448\u0438 \u0440\u043e\u043b\u0438:* ",
        "Selfrooms": {},
        "Mafrooms": {},
        "IgnoreChannels": [],
        "IgnoreRoles": [],
        "card": "wave.png",
        "text_color": "#d0ed2b",
        "bar_color": "#ec5252",
        "blend": 1,
        "USERS": {
            "228537642583588864": {
                "WARNS": 0,
                "CAPS": 0,
                "SCR": 0,
                "LvL": 1
            },
            "466609421863354388": {
                "WARNS": 0,
                "CAPS": 0,
                "SCR": 0,
                "LvL": 1
            },
            "984816758441517157": {
                "WARNS": 0,
                "CAPS": 0,
                "SCR": 0,
                "LvL": 1
            }
        }
    },
    "981257625696075896": {
        "COLOR": "0x0000FF",
        "ErCOLOR": "0x8B0000",
        "JoinRoles": [],
        "ROLES": {},
        "actmoduls": "",
        "nCaps": -1,
        "nWarns": 10,
        "idAdminchennel": "0",
        "idMainch": "0",
        "selfRoom": "0",
        "BADWORDS": [],
        "LINKS": [],
        "PREFIX": "~",
        "JNMSG": "",
        "SelfTitle": "*\u0412\u044b\u0431\u0435\u0440\u0438\u0442\u0435 \u0432\u0430\u0448\u0438 \u0440\u043e\u043b\u0438:* ",
        "Selfrooms": {},
        "Mafrooms": {},
        "IgnoreChannels": [],
        "IgnoreRoles": [],
        "card": "wave.png",
        "text_color": "#d0ed2b",
        "bar_color": "#ec5252",
        "blend": 1,
        "USERS": {
            "224930494314315776": {
                "WARNS": 0,
                "CAPS": 0,
                "SCR": 0,
                "LvL": 1
            },
            "281070552465145857": {
                "WARNS": 0,
                "CAPS": 0,
                "SCR": 0,
                "LvL": 1
            },
            "347027993530728448": {
                "WARNS": 0,
                "CAPS": 0,
                "SCR": 0,
                "LvL": 1
            },
            "352413086096818176": {
                "WARNS": 0,
                "CAPS": 0,
                "SCR": 0,
                "LvL": 1
            },
            "406124614729859073": {
                "WARNS": 0,
                "CAPS": 0,
                "SCR": 0,
                "LvL": 1
            },
            "466609421863354388": {
                "WARNS": 0,
                "CAPS": 0,
                "SCR": 16,
                "LvL": 3
            },
            "544279889470291989": {
                "WARNS": 0,
                "CAPS": 0,
                "SCR": 0,
                "LvL": 1
            },
            "547077175308713994": {
                "WARNS": 0,
                "CAPS": 0,
                "SCR": 0,
                "LvL": 1
            },
            "583722104059592757": {
                "WARNS": 0,
                "CAPS": 0,
                "SCR": 0,
                "LvL": 1
            },
            "666768779174346782": {
                "WARNS": 0,
                "CAPS": 0,
                "SCR": 0,
                "LvL": 1
            },
            "742045972280115231": {
                "WARNS": 0,
                "CAPS": 0,
                "SCR": 0,
                "LvL": 1
            },
            "758734389072625685": {
                "WARNS": 0,
                "CAPS": 0,
                "SCR": 0,
                "LvL": 1
            },
            "840307986228707368": {
                "WARNS": 0,
                "CAPS": 0,
                "SCR": 0,
                "LvL": 1
            },
            "858638662160613376": {
                "WARNS": 0,
                "CAPS": 0,
                "SCR": 0,
                "LvL": 1
            },
            "935190075430543461": {
                "WARNS": 0,
                "CAPS": 0,
                "SCR": 0,
                "LvL": 1
            },
            "981511682960547860": {
                "WARNS": 0,
                "CAPS": 0,
                "SCR": 0,
                "LvL": 1
            },
            "984816758441517157": {
                "WARNS": 0,
                "CAPS": 0,
                "SCR": 0,
                "LvL": 1
            },
            "992771455500681307": {
                "WARNS": 0,
                "CAPS": 0,
                "SCR": 0,
                "LvL": 1
            }
        }
    },
    "986005469447487570": {
        "COLOR": "0x0000FF",
        "ErCOLOR": "0x8B0000",
        "JoinRoles": [],
        "ROLES": {},
        "actmoduls": "",
        "nCaps": -1,
        "nWarns": 10,
        "idAdminchennel": "0",
        "idMainch": "0",
        "selfRoom": "0",
        "BADWORDS": [],
        "LINKS": [],
        "PREFIX": "~",
        "JNMSG": "",
        "SelfTitle": "*\u0412\u044b\u0431\u0435\u0440\u0438\u0442\u0435 \u0432\u0430\u0448\u0438 \u0440\u043e\u043b\u0438:* ",
        "Selfrooms": {},
        "Mafrooms": {},
        "IgnoreChannels": [],
        "IgnoreRoles": [],
        "card": "wave.png",
        "text_color": "#d0ed2b",
        "bar_color": "#ec5252",
        "blend": 1,
        "USERS": {
            "466609421863354388": {
                "WARNS": 0,
                "CAPS": 0,
                "SCR": 0,
                "LvL": 1
            },
            "514329860852809740": {
                "WARNS": 0,
                "CAPS": 0,
                "SCR": 0,
                "LvL": 1
            },
            "758734389072625685": {
                "WARNS": 0,
                "CAPS": 0,
                "SCR": 0,
                "LvL": 1
            },
            "984816758441517157": {
                "WARNS": 0,
                "CAPS": 0,
                "SCR": 0,
                "LvL": 1
            }
        }
    },
    "989015983534522428": {
        "COLOR": "0x0000FF",
        "ErCOLOR": "0x8B0000",
        "JoinRoles": [],
        "ROLES": {},
        "actmoduls": "",
        "nCaps": -1,
        "nWarns": 10,
        "idAdminchennel": "0",
        "idMainch": "0",
        "selfRoom": "0",
        "BADWORDS": [],
        "LINKS": [],
        "PREFIX": "~",
        "JNMSG": "",
        "SelfTitle": "*\u0412\u044b\u0431\u0435\u0440\u0438\u0442\u0435 \u0432\u0430\u0448\u0438 \u0440\u043e\u043b\u0438:* ",
        "Selfrooms": {},
        "Mafrooms": {},
        "IgnoreChannels": [],
        "IgnoreRoles": [],
        "card": "wave.png",
        "text_color": "#d0ed2b",
        "bar_color": "#ec5252",
        "blend": 1,
        "USERS": {
            "466609421863354388": {
                "WARNS": 0,
                "CAPS": 0,
                "SCR": 0,
                "LvL": 1
            },
            "984816758441517157": {
                "WARNS": 0,
                "CAPS": 0,
                "SCR": 0,
                "LvL": 1
            }
        }
    }
}